odoo/addons/account_vendor_bank_account_default_purchase/README.rst
odoo/addons/account_vendor_bank_account_default_purchase/__init__.py
odoo/addons/account_vendor_bank_account_default_purchase/__manifest__.py
odoo/addons/account_vendor_bank_account_default_purchase/i18n/account_vendor_bank_account_default_purchase.pot
odoo/addons/account_vendor_bank_account_default_purchase/i18n/ca.po
odoo/addons/account_vendor_bank_account_default_purchase/i18n/es.po
odoo/addons/account_vendor_bank_account_default_purchase/i18n/it.po
odoo/addons/account_vendor_bank_account_default_purchase/models/__init__.py
odoo/addons/account_vendor_bank_account_default_purchase/models/purchase_order.py
odoo/addons/account_vendor_bank_account_default_purchase/readme/CONFIGURE.md
odoo/addons/account_vendor_bank_account_default_purchase/readme/CONTRIBUTORS.md
odoo/addons/account_vendor_bank_account_default_purchase/readme/DESCRIPTION.md
odoo/addons/account_vendor_bank_account_default_purchase/readme/ROADMAP.md
odoo/addons/account_vendor_bank_account_default_purchase/readme/USAGE.md
odoo/addons/account_vendor_bank_account_default_purchase/static/description/icon.png
odoo/addons/account_vendor_bank_account_default_purchase/static/description/icon.svg
odoo/addons/account_vendor_bank_account_default_purchase/static/description/index.html
odoo/addons/account_vendor_bank_account_default_purchase/tests/__init__.py
odoo/addons/account_vendor_bank_account_default_purchase/tests/test_account_vendor_bank_account_default.py
odoo_addon_account_vendor_bank_account_default_purchase-17.0.1.0.0.7.dist-info/METADATA
odoo_addon_account_vendor_bank_account_default_purchase-17.0.1.0.0.7.dist-info/WHEEL
odoo_addon_account_vendor_bank_account_default_purchase-17.0.1.0.0.7.dist-info/top_level.txt
odoo_addon_account_vendor_bank_account_default_purchase-17.0.1.0.0.7.dist-info/RECORD
